{"subject":{"name":"Paolo","surname":"Valletta","age":25,"gender":"male","hasTakenMedicines":false,"listOfMedicinesText":"25"},"rounds":[{"roundNumber":1,"answersArray":[{"isYes":true,"isTarget":false,"questionStartingTimeInMillis":1562271264570,"startWindowTimestamp":1562271265021,"answerTimestamp":1562271266021,"endingWindowTimestamp":1562271268021},{"isYes":false,"isTarget":false,"questionStartingTimeInMillis":1562271268025,"startWindowTimestamp":1562271268095,"answerTimestamp":1562271269095,"endingWindowTimestamp":1562271271095},{"isYes":false,"isTarget":false,"questionStartingTimeInMillis":1562271271098,"startWindowTimestamp":1562271270993,"answerTimestamp":1562271271993,"endingWindowTimestamp":1562271273993},{"isYes":false,"isTarget":false,"questionStartingTimeInMillis":1562271273994,"startWindowTimestamp":1562271273730,"answerTimestamp":1562271274730,"endingWindowTimestamp":1562271276730},{"isYes":false,"isTarget":true,"questionStartingTimeInMillis":1562271276733,"startWindowTimestamp":1562271277579,"answerTimestamp":1562271278579,"endingWindowTimestamp":1562271280579},{"isYes":true,"isTarget":false,"questionStartingTimeInMillis":1562271280581,"startWindowTimestamp":1562271281130,"answerTimestamp":1562271282130,"endingWindowTimestamp":1562271284130},{"isYes":false,"isTarget":true,"questionStartingTimeInMillis":1562271284132,"startWindowTimestamp":1562271284273,"answerTimestamp":1562271285273,"endingWindowTimestamp":1562271287273},{"isYes":false,"isTarget":false,"questionStartingTimeInMillis":1562271287275,"startWindowTimestamp":1562271287326,"answerTimestamp":1562271288326,"endingWindowTimestamp":1562271290326},{"isYes":false,"isTarget":false,"questionStartingTimeInMillis":1562271290328,"startWindowTimestamp":1562271290826,"answerTimestamp":1562271291826,"endingWindowTimestamp":1562271293826},{"isYes":false,"isTarget":false,"questionStartingTimeInMillis":1562271293828,"startWindowTimestamp":1562271293544,"answerTimestamp":1562271294544,"endingWindowTimestamp":1562271296544},{"isYes":false,"isTarget":true,"questionStartingTimeInMillis":1562271296546,"startWindowTimestamp":1562271297400,"answerTimestamp":1562271298400,"endingWindowTimestamp":1562271300400},{"isYes":false,"isTarget":false,"questionStartingTimeInMillis":1562271300402,"startWindowTimestamp":1562271300407,"answerTimestamp":1562271301407,"endingWindowTimestamp":1562271303407},{"isYes":false,"isTarget":false,"questionStartingTimeInMillis":1562271303409,"startWindowTimestamp":1562271303059,"answerTimestamp":1562271304059,"endingWindowTimestamp":1562271306059},{"isYes":false,"isTarget":false,"questionStartingTimeInMillis":1562271306061,"startWindowTimestamp":1562271305742,"answerTimestamp":1562271306742,"endingWindowTimestamp":1562271308742},{"isYes":false,"isTarget":false,"questionStartingTimeInMillis":1562271308744,"startWindowTimestamp":1562271308792,"answerTimestamp":1562271309792,"endingWindowTimestamp":1562271311792},{"isYes":false,"isTarget":false,"questionStartingTimeInMillis":1562271311794,"startWindowTimestamp":1562271311639,"answerTimestamp":1562271312639,"endingWindowTimestamp":1562271314639},{"isYes":false,"isTarget":false,"questionStartingTimeInMillis":1562271314640,"startWindowTimestamp":1562271314374,"answerTimestamp":1562271315374,"endingWindowTimestamp":1562271317374},{"isYes":false,"isTarget":false,"questionStartingTimeInMillis":1562271317375,"startWindowTimestamp":1562271317058,"answerTimestamp":1562271318058,"endingWindowTimestamp":1562271320058},{"isYes":false,"isTarget":false,"questionStartingTimeInMillis":1562271320060,"startWindowTimestamp":1562271319938,"answerTimestamp":1562271320938,"endingWindowTimestamp":1562271322938},{"isYes":true,"isTarget":false,"questionStartingTimeInMillis":1562271322941,"startWindowTimestamp":1562271322886,"answerTimestamp":1562271323886,"endingWindowTimestamp":1562271325886},{"isYes":false,"isTarget":false,"questionStartingTimeInMillis":1562271325888,"startWindowTimestamp":1562271325709,"answerTimestamp":1562271326709,"endingWindowTimestamp":1562271328709},{"isYes":false,"isTarget":false,"questionStartingTimeInMillis":1562271328711,"startWindowTimestamp":1562271328350,"answerTimestamp":1562271329350,"endingWindowTimestamp":1562271331350},{"isYes":false,"isTarget":false,"questionStartingTimeInMillis":1562271331352,"startWindowTimestamp":1562271331092,"answerTimestamp":1562271332092,"endingWindowTimestamp":1562271334092},{"isYes":true,"isTarget":false,"questionStartingTimeInMillis":1562271334094,"startWindowTimestamp":1562271334227,"answerTimestamp":1562271335227,"endingWindowTimestamp":1562271337227},{"isYes":false,"isTarget":false,"questionStartingTimeInMillis":1562271337229,"startWindowTimestamp":1562271336921,"answerTimestamp":1562271337921,"endingWindowTimestamp":1562271339921},{"isYes":false,"isTarget":false,"questionStartingTimeInMillis":1562271339923,"startWindowTimestamp":1562271339710,"answerTimestamp":1562271340710,"endingWindowTimestamp":1562271342710},{"isYes":false,"isTarget":false,"questionStartingTimeInMillis":1562271342712,"startWindowTimestamp":1562271342632,"answerTimestamp":1562271343632,"endingWindowTimestamp":1562271345632},{"isYes":false,"isTarget":false,"questionStartingTimeInMillis":1562271345634,"startWindowTimestamp":1562271345326,"answerTimestamp":1562271346326,"endingWindowTimestamp":1562271348326},{"isYes":false,"isTarget":true,"questionStartingTimeInMillis":1562271348328,"startWindowTimestamp":1562271348196,"answerTimestamp":1562271349196,"endingWindowTimestamp":1562271351196},{"isYes":false,"isTarget":false,"questionStartingTimeInMillis":1562271351210,"startWindowTimestamp":1562271350883,"answerTimestamp":1562271351883,"endingWindowTimestamp":1562271353883},{"isYes":false,"isTarget":false,"questionStartingTimeInMillis":1562271353885,"startWindowTimestamp":1562271353524,"answerTimestamp":1562271354524,"endingWindowTimestamp":1562271356524},{"isYes":false,"isTarget":false,"questionStartingTimeInMillis":1562271356526,"startWindowTimestamp":1562271356261,"answerTimestamp":1562271357261,"endingWindowTimestamp":1562271359261},{"isYes":false,"isTarget":false,"questionStartingTimeInMillis":1562271359263,"startWindowTimestamp":1562271358920,"answerTimestamp":1562271359920,"endingWindowTimestamp":1562271361920},{"isYes":false,"isTarget":false,"questionStartingTimeInMillis":1562271361922,"startWindowTimestamp":1562271361732,"answerTimestamp":1562271362732,"endingWindowTimestamp":1562271364732},{"isYes":false,"isTarget":false,"questionStartingTimeInMillis":1562271364735,"startWindowTimestamp":1562271364535,"answerTimestamp":1562271365535,"endingWindowTimestamp":1562271367535},{"isYes":false,"isTarget":false,"questionStartingTimeInMillis":1562271367537,"startWindowTimestamp":1562271367594,"answerTimestamp":1562271368594,"endingWindowTimestamp":1562271370594},{"isYes":false,"isTarget":false,"questionStartingTimeInMillis":1562271370596,"startWindowTimestamp":1562271370280,"answerTimestamp":1562271371280,"endingWindowTimestamp":1562271373280},{"isYes":false,"isTarget":false,"questionStartingTimeInMillis":1562271373281,"startWindowTimestamp":1562271372820,"answerTimestamp":1562271373820,"endingWindowTimestamp":1562271375820},{"isYes":false,"isTarget":false,"questionStartingTimeInMillis":1562271375822,"startWindowTimestamp":1562271375472,"answerTimestamp":1562271376472,"endingWindowTimestamp":1562271378472}]}]}