{"subject":{"name":"Stefano","surname":"Zennaro","age":26,"gender":"male","hasTakenMedicines":false,"listOfMedicinesText":"26"},"rounds":[{"roundNumber":1,"answersArray":[{"isYes":false,"isTarget":false,"questionStartingTimeInMillis":1562332159143,"startWindowTimestamp":1562332159489,"answerTimestamp":1562332160489,"endingWindowTimestamp":1562332162489},{"isYes":false,"isTarget":false,"questionStartingTimeInMillis":1562332162492,"startWindowTimestamp":1562332162657,"answerTimestamp":1562332163657,"endingWindowTimestamp":1562332165657},{"isYes":false,"isTarget":false,"questionStartingTimeInMillis":1562332165659,"startWindowTimestamp":1562332165928,"answerTimestamp":1562332166928,"endingWindowTimestamp":1562332168928},{"isYes":false,"isTarget":false,"questionStartingTimeInMillis":1562332168930,"startWindowTimestamp":1562332168716,"answerTimestamp":1562332169716,"endingWindowTimestamp":1562332171716},{"isYes":false,"isTarget":false,"questionStartingTimeInMillis":1562332171717,"startWindowTimestamp":1562332171493,"answerTimestamp":1562332172493,"endingWindowTimestamp":1562332174493},{"isYes":false,"isTarget":false,"questionStartingTimeInMillis":1562332174495,"startWindowTimestamp":1562332174269,"answerTimestamp":1562332175269,"endingWindowTimestamp":1562332177269},{"isYes":true,"isTarget":false,"questionStartingTimeInMillis":1562332177270,"startWindowTimestamp":1562332179248,"answerTimestamp":1562332180248,"endingWindowTimestamp":1562332182248},{"isYes":false,"isTarget":false,"questionStartingTimeInMillis":1562332182250,"startWindowTimestamp":1562332182363,"answerTimestamp":1562332183363,"endingWindowTimestamp":1562332185363},{"isYes":false,"isTarget":false,"questionStartingTimeInMillis":1562332185366,"startWindowTimestamp":1562332185208,"answerTimestamp":1562332186208,"endingWindowTimestamp":1562332188208},{"isYes":false,"isTarget":false,"questionStartingTimeInMillis":1562332188210,"startWindowTimestamp":1562332188038,"answerTimestamp":1562332189038,"endingWindowTimestamp":1562332191038},{"isYes":false,"isTarget":true,"questionStartingTimeInMillis":1562332191041,"startWindowTimestamp":1562332191264,"answerTimestamp":1562332192264,"endingWindowTimestamp":1562332194264},{"isYes":false,"isTarget":false,"questionStartingTimeInMillis":1562332194267,"startWindowTimestamp":1562332194291,"answerTimestamp":1562332195291,"endingWindowTimestamp":1562332197291},{"isYes":false,"isTarget":false,"questionStartingTimeInMillis":1562332197293,"startWindowTimestamp":1562332197356,"answerTimestamp":1562332198356,"endingWindowTimestamp":1562332200356},{"isYes":false,"isTarget":false,"questionStartingTimeInMillis":1562332200358,"startWindowTimestamp":1562332200047,"answerTimestamp":1562332201047,"endingWindowTimestamp":1562332203047},{"isYes":false,"isTarget":false,"questionStartingTimeInMillis":1562332203051,"startWindowTimestamp":1562332203064,"answerTimestamp":1562332204064,"endingWindowTimestamp":1562332206064},{"isYes":false,"isTarget":false,"questionStartingTimeInMillis":1562332206066,"startWindowTimestamp":1562332206105,"answerTimestamp":1562332207105,"endingWindowTimestamp":1562332209105},{"isYes":false,"isTarget":false,"questionStartingTimeInMillis":1562332209107,"startWindowTimestamp":1562332209576,"answerTimestamp":1562332210576,"endingWindowTimestamp":1562332212576},{"isYes":false,"isTarget":false,"questionStartingTimeInMillis":1562332212578,"startWindowTimestamp":1562332212271,"answerTimestamp":1562332213271,"endingWindowTimestamp":1562332215271},{"isYes":false,"isTarget":true,"questionStartingTimeInMillis":1562332215273,"startWindowTimestamp":1562332215101,"answerTimestamp":1562332216101,"endingWindowTimestamp":1562332218101},{"isYes":false,"isTarget":false,"questionStartingTimeInMillis":1562332218103,"startWindowTimestamp":1562332217735,"answerTimestamp":1562332218735,"endingWindowTimestamp":1562332220735},{"isYes":false,"isTarget":false,"questionStartingTimeInMillis":1562332220737,"startWindowTimestamp":1562332220722,"answerTimestamp":1562332221722,"endingWindowTimestamp":1562332223722},{"isYes":false,"isTarget":false,"questionStartingTimeInMillis":1562332223724,"startWindowTimestamp":1562332223484,"answerTimestamp":1562332224484,"endingWindowTimestamp":1562332226484},{"isYes":false,"isTarget":false,"questionStartingTimeInMillis":1562332226486,"startWindowTimestamp":1562332226619,"answerTimestamp":1562332227619,"endingWindowTimestamp":1562332229619},{"isYes":false,"isTarget":false,"questionStartingTimeInMillis":1562332229620,"startWindowTimestamp":1562332229485,"answerTimestamp":1562332230485,"endingWindowTimestamp":1562332232485},{"isYes":false,"isTarget":false,"questionStartingTimeInMillis":1562332232487,"startWindowTimestamp":1562332232318,"answerTimestamp":1562332233318,"endingWindowTimestamp":1562332235318},{"isYes":false,"isTarget":false,"questionStartingTimeInMillis":1562332235320,"startWindowTimestamp":1562332235145,"answerTimestamp":1562332236145,"endingWindowTimestamp":1562332238145},{"isYes":true,"isTarget":false,"questionStartingTimeInMillis":1562332238147,"startWindowTimestamp":1562332238210,"answerTimestamp":1562332239210,"endingWindowTimestamp":1562332241210},{"isYes":false,"isTarget":false,"questionStartingTimeInMillis":1562332241212,"startWindowTimestamp":1562332241560,"answerTimestamp":1562332242560,"endingWindowTimestamp":1562332244560},{"isYes":false,"isTarget":true,"questionStartingTimeInMillis":1562332244562,"startWindowTimestamp":1562332244228,"answerTimestamp":1562332245228,"endingWindowTimestamp":1562332247228},{"isYes":false,"isTarget":false,"questionStartingTimeInMillis":1562332247229,"startWindowTimestamp":1562332246987,"answerTimestamp":1562332247987,"endingWindowTimestamp":1562332249987},{"isYes":false,"isTarget":false,"questionStartingTimeInMillis":1562332249988,"startWindowTimestamp":1562332249783,"answerTimestamp":1562332250783,"endingWindowTimestamp":1562332252783},{"isYes":false,"isTarget":true,"questionStartingTimeInMillis":1562332252784,"startWindowTimestamp":1562332252621,"answerTimestamp":1562332253621,"endingWindowTimestamp":1562332255621},{"isYes":false,"isTarget":false,"questionStartingTimeInMillis":1562332255623,"startWindowTimestamp":1562332255655,"answerTimestamp":1562332256655,"endingWindowTimestamp":1562332258655},{"isYes":false,"isTarget":false,"questionStartingTimeInMillis":1562332258657,"startWindowTimestamp":1562332258367,"answerTimestamp":1562332259367,"endingWindowTimestamp":1562332261367},{"isYes":false,"isTarget":false,"questionStartingTimeInMillis":1562332261368,"startWindowTimestamp":1562332261197,"answerTimestamp":1562332262197,"endingWindowTimestamp":1562332264197},{"isYes":false,"isTarget":false,"questionStartingTimeInMillis":1562332264199,"startWindowTimestamp":1562332263982,"answerTimestamp":1562332264982,"endingWindowTimestamp":1562332266982},{"isYes":true,"isTarget":false,"questionStartingTimeInMillis":1562332266984,"startWindowTimestamp":1562332267068,"answerTimestamp":1562332268068,"endingWindowTimestamp":1562332270068},{"isYes":false,"isTarget":false,"questionStartingTimeInMillis":1562332270070,"startWindowTimestamp":1562332269805,"answerTimestamp":1562332270805,"endingWindowTimestamp":1562332272805},{"isYes":false,"isTarget":false,"questionStartingTimeInMillis":1562332272807,"startWindowTimestamp":1562332272448,"answerTimestamp":1562332273448,"endingWindowTimestamp":1562332275448}]}]}