{"subject":{"name":"Alfonso","surname":"Dipace","age":22,"gender":"male","hasTakenMedicines":false,"listOfMedicinesText":"22"},"rounds":[{"roundNumber":1,"answersArray":[{"isYes":false,"isTarget":false,"questionStartingTimeInMillis":1562661570170,"startWindowTimestamp":1562661570731,"answerTimestamp":1562661571731,"endingWindowTimestamp":1562661573731},{"isYes":true,"isTarget":false,"questionStartingTimeInMillis":1562661573734,"startWindowTimestamp":1562661573857,"answerTimestamp":1562661574857,"endingWindowTimestamp":1562661576857},{"isYes":false,"isTarget":false,"questionStartingTimeInMillis":1562661576860,"startWindowTimestamp":1562661576890,"answerTimestamp":1562661577890,"endingWindowTimestamp":1562661579890},{"isYes":false,"isTarget":false,"questionStartingTimeInMillis":1562661579893,"startWindowTimestamp":1562661579660,"answerTimestamp":1562661580660,"endingWindowTimestamp":1562661582660},{"isYes":false,"isTarget":false,"questionStartingTimeInMillis":1562661582664,"startWindowTimestamp":1562661582825,"answerTimestamp":1562661583825,"endingWindowTimestamp":1562661585825},{"isYes":false,"isTarget":false,"questionStartingTimeInMillis":1562661585828,"startWindowTimestamp":1562661585873,"answerTimestamp":1562661586873,"endingWindowTimestamp":1562661588873},{"isYes":false,"isTarget":true,"questionStartingTimeInMillis":1562661588876,"startWindowTimestamp":1562661588974,"answerTimestamp":1562661589974,"endingWindowTimestamp":1562661591974},{"isYes":false,"isTarget":false,"questionStartingTimeInMillis":1562661591976,"startWindowTimestamp":1562661592216,"answerTimestamp":1562661593216,"endingWindowTimestamp":1562661595216},{"isYes":false,"isTarget":true,"questionStartingTimeInMillis":1562661595219,"startWindowTimestamp":1562661595486,"answerTimestamp":1562661596486,"endingWindowTimestamp":1562661598486},{"isYes":false,"isTarget":false,"questionStartingTimeInMillis":1562661598489,"startWindowTimestamp":1562661598185,"answerTimestamp":1562661599185,"endingWindowTimestamp":1562661601185},{"isYes":false,"isTarget":false,"questionStartingTimeInMillis":1562661601187,"startWindowTimestamp":1562661600947,"answerTimestamp":1562661601947,"endingWindowTimestamp":1562661603947},{"isYes":false,"isTarget":false,"questionStartingTimeInMillis":1562661603953,"startWindowTimestamp":1562661603856,"answerTimestamp":1562661604856,"endingWindowTimestamp":1562661606856},{"isYes":false,"isTarget":true,"questionStartingTimeInMillis":1562661606859,"startWindowTimestamp":1562661606715,"answerTimestamp":1562661607715,"endingWindowTimestamp":1562661609715},{"isYes":true,"isTarget":false,"questionStartingTimeInMillis":1562661609718,"startWindowTimestamp":1562661609725,"answerTimestamp":1562661610725,"endingWindowTimestamp":1562661612725},{"isYes":false,"isTarget":false,"questionStartingTimeInMillis":1562661612727,"startWindowTimestamp":1562661612435,"answerTimestamp":1562661613435,"endingWindowTimestamp":1562661615435},{"isYes":false,"isTarget":false,"questionStartingTimeInMillis":1562661615444,"startWindowTimestamp":1562661615687,"answerTimestamp":1562661616687,"endingWindowTimestamp":1562661618687},{"isYes":false,"isTarget":false,"questionStartingTimeInMillis":1562661618689,"startWindowTimestamp":1562661618795,"answerTimestamp":1562661619795,"endingWindowTimestamp":1562661621795},{"isYes":false,"isTarget":false,"questionStartingTimeInMillis":1562661621797,"startWindowTimestamp":1562661621512,"answerTimestamp":1562661622512,"endingWindowTimestamp":1562661624512},{"isYes":false,"isTarget":false,"questionStartingTimeInMillis":1562661624514,"startWindowTimestamp":1562661624327,"answerTimestamp":1562661625327,"endingWindowTimestamp":1562661627327},{"isYes":true,"isTarget":false,"questionStartingTimeInMillis":1562661627329,"startWindowTimestamp":1562661627215,"answerTimestamp":1562661628215,"endingWindowTimestamp":1562661630215},{"isYes":false,"isTarget":false,"questionStartingTimeInMillis":1562661630223,"startWindowTimestamp":1562661630088,"answerTimestamp":1562661631088,"endingWindowTimestamp":1562661633088},{"isYes":false,"isTarget":false,"questionStartingTimeInMillis":1562661633091,"startWindowTimestamp":1562661633087,"answerTimestamp":1562661634087,"endingWindowTimestamp":1562661636087},{"isYes":false,"isTarget":false,"questionStartingTimeInMillis":1562661636089,"startWindowTimestamp":1562661636447,"answerTimestamp":1562661637447,"endingWindowTimestamp":1562661639447},{"isYes":false,"isTarget":true,"questionStartingTimeInMillis":1562661639449,"startWindowTimestamp":1562661639582,"answerTimestamp":1562661640582,"endingWindowTimestamp":1562661642582},{"isYes":false,"isTarget":false,"questionStartingTimeInMillis":1562661642584,"startWindowTimestamp":1562661642336,"answerTimestamp":1562661643336,"endingWindowTimestamp":1562661645336},{"isYes":false,"isTarget":false,"questionStartingTimeInMillis":1562661645338,"startWindowTimestamp":1562661645125,"answerTimestamp":1562661646125,"endingWindowTimestamp":1562661648125},{"isYes":false,"isTarget":false,"questionStartingTimeInMillis":1562661648127,"startWindowTimestamp":1562661647927,"answerTimestamp":1562661648927,"endingWindowTimestamp":1562661650927},{"isYes":false,"isTarget":false,"questionStartingTimeInMillis":1562661650929,"startWindowTimestamp":1562661650466,"answerTimestamp":1562661651466,"endingWindowTimestamp":1562661653466},{"isYes":false,"isTarget":false,"questionStartingTimeInMillis":1562661653468,"startWindowTimestamp":1562661653067,"answerTimestamp":1562661654067,"endingWindowTimestamp":1562661656067},{"isYes":false,"isTarget":false,"questionStartingTimeInMillis":1562661656069,"startWindowTimestamp":1562661655675,"answerTimestamp":1562661656675,"endingWindowTimestamp":1562661658675},{"isYes":false,"isTarget":false,"questionStartingTimeInMillis":1562661658677,"startWindowTimestamp":1562661658489,"answerTimestamp":1562661659489,"endingWindowTimestamp":1562661661489},{"isYes":false,"isTarget":false,"questionStartingTimeInMillis":1562661661491,"startWindowTimestamp":1562661661062,"answerTimestamp":1562661662062,"endingWindowTimestamp":1562661664062},{"isYes":true,"isTarget":false,"questionStartingTimeInMillis":1562661664064,"startWindowTimestamp":1562661664055,"answerTimestamp":1562661665055,"endingWindowTimestamp":1562661667055},{"isYes":false,"isTarget":false,"questionStartingTimeInMillis":1562661667058,"startWindowTimestamp":1562661666912,"answerTimestamp":1562661667912,"endingWindowTimestamp":1562661669912},{"isYes":false,"isTarget":false,"questionStartingTimeInMillis":1562661669914,"startWindowTimestamp":1562661669502,"answerTimestamp":1562661670502,"endingWindowTimestamp":1562661672502},{"isYes":false,"isTarget":false,"questionStartingTimeInMillis":1562661672504,"startWindowTimestamp":1562661672176,"answerTimestamp":1562661673176,"endingWindowTimestamp":1562661675176},{"isYes":false,"isTarget":false,"questionStartingTimeInMillis":1562661675179,"startWindowTimestamp":1562661675093,"answerTimestamp":1562661676093,"endingWindowTimestamp":1562661678093},{"isYes":false,"isTarget":false,"questionStartingTimeInMillis":1562661678095,"startWindowTimestamp":1562661677885,"answerTimestamp":1562661678885,"endingWindowTimestamp":1562661680885},{"isYes":false,"isTarget":false,"questionStartingTimeInMillis":1562661680887,"startWindowTimestamp":1562661680505,"answerTimestamp":1562661681505,"endingWindowTimestamp":1562661683505}]}]}