{"subject":{"name":"Renato","surname":"Gabriele","age":30,"gender":"male","hasTakenMedicines":false,"listOfMedicinesText":"30"},"rounds":[{"roundNumber":1,"answersArray":[{"isYes":false,"isTarget":false,"questionStartingTimeInMillis":1562425854528,"startWindowTimestamp":1562425854966,"answerTimestamp":1562425855966,"endingWindowTimestamp":1562425857966},{"isYes":false,"isTarget":false,"questionStartingTimeInMillis":1562425857969,"startWindowTimestamp":1562425858224,"answerTimestamp":1562425859224,"endingWindowTimestamp":1562425861224},{"isYes":false,"isTarget":false,"questionStartingTimeInMillis":1562425861226,"startWindowTimestamp":1562425861138,"answerTimestamp":1562425862138,"endingWindowTimestamp":1562425864138},{"isYes":false,"isTarget":false,"questionStartingTimeInMillis":1562425864140,"startWindowTimestamp":1562425864522,"answerTimestamp":1562425865522,"endingWindowTimestamp":1562425867522},{"isYes":false,"isTarget":false,"questionStartingTimeInMillis":1562425867525,"startWindowTimestamp":1562425867925,"answerTimestamp":1562425868925,"endingWindowTimestamp":1562425870925},{"isYes":false,"isTarget":false,"questionStartingTimeInMillis":1562425870927,"startWindowTimestamp":1562425871073,"answerTimestamp":1562425872073,"endingWindowTimestamp":1562425874073},{"isYes":false,"isTarget":false,"questionStartingTimeInMillis":1562425874075,"startWindowTimestamp":1562425874410,"answerTimestamp":1562425875410,"endingWindowTimestamp":1562425877410},{"isYes":true,"isTarget":false,"questionStartingTimeInMillis":1562425877413,"startWindowTimestamp":1562425877709,"answerTimestamp":1562425878709,"endingWindowTimestamp":1562425880709},{"isYes":false,"isTarget":false,"questionStartingTimeInMillis":1562425880710,"startWindowTimestamp":1562425880854,"answerTimestamp":1562425881854,"endingWindowTimestamp":1562425883854},{"isYes":false,"isTarget":false,"questionStartingTimeInMillis":1562425883857,"startWindowTimestamp":1562425883934,"answerTimestamp":1562425884934,"endingWindowTimestamp":1562425886934},{"isYes":false,"isTarget":true,"questionStartingTimeInMillis":1562425886937,"startWindowTimestamp":1562425886925,"answerTimestamp":1562425887925,"endingWindowTimestamp":1562425889925},{"isYes":false,"isTarget":false,"questionStartingTimeInMillis":1562425889927,"startWindowTimestamp":1562425890266,"answerTimestamp":1562425891266,"endingWindowTimestamp":1562425893266},{"isYes":false,"isTarget":false,"questionStartingTimeInMillis":1562425893268,"startWindowTimestamp":1562425893607,"answerTimestamp":1562425894607,"endingWindowTimestamp":1562425896607},{"isYes":false,"isTarget":false,"questionStartingTimeInMillis":1562425896611,"startWindowTimestamp":1562425896507,"answerTimestamp":1562425897507,"endingWindowTimestamp":1562425899507},{"isYes":true,"isTarget":false,"questionStartingTimeInMillis":1562425899510,"startWindowTimestamp":1562425899336,"answerTimestamp":1562425900336,"endingWindowTimestamp":1562425902336},{"isYes":false,"isTarget":false,"questionStartingTimeInMillis":1562425902338,"startWindowTimestamp":1562425902091,"answerTimestamp":1562425903091,"endingWindowTimestamp":1562425905091},{"isYes":false,"isTarget":false,"questionStartingTimeInMillis":1562425905093,"startWindowTimestamp":1562425905098,"answerTimestamp":1562425906098,"endingWindowTimestamp":1562425908098},{"isYes":true,"isTarget":false,"questionStartingTimeInMillis":1562425908100,"startWindowTimestamp":1562425908066,"answerTimestamp":1562425909066,"endingWindowTimestamp":1562425911066},{"isYes":false,"isTarget":false,"questionStartingTimeInMillis":1562425911068,"startWindowTimestamp":1562425910903,"answerTimestamp":1562425911903,"endingWindowTimestamp":1562425913903},{"isYes":false,"isTarget":false,"questionStartingTimeInMillis":1562425913905,"startWindowTimestamp":1562425914085,"answerTimestamp":1562425915085,"endingWindowTimestamp":1562425917085},{"isYes":false,"isTarget":true,"questionStartingTimeInMillis":1562425917087,"startWindowTimestamp":1562425917274,"answerTimestamp":1562425918274,"endingWindowTimestamp":1562425920274},{"isYes":false,"isTarget":false,"questionStartingTimeInMillis":1562425920276,"startWindowTimestamp":1562425920127,"answerTimestamp":1562425921127,"endingWindowTimestamp":1562425923127},{"isYes":false,"isTarget":false,"questionStartingTimeInMillis":1562425923128,"startWindowTimestamp":1562425923078,"answerTimestamp":1562425924078,"endingWindowTimestamp":1562425926078},{"isYes":true,"isTarget":false,"questionStartingTimeInMillis":1562425926079,"startWindowTimestamp":1562425925925,"answerTimestamp":1562425926925,"endingWindowTimestamp":1562425928925},{"isYes":false,"isTarget":false,"questionStartingTimeInMillis":1562425928927,"startWindowTimestamp":1562425928704,"answerTimestamp":1562425929704,"endingWindowTimestamp":1562425931704},{"isYes":false,"isTarget":false,"questionStartingTimeInMillis":1562425931706,"startWindowTimestamp":1562425931495,"answerTimestamp":1562425932495,"endingWindowTimestamp":1562425934495},{"isYes":false,"isTarget":false,"questionStartingTimeInMillis":1562425934496,"startWindowTimestamp":1562425934513,"answerTimestamp":1562425935513,"endingWindowTimestamp":1562425937513},{"isYes":false,"isTarget":true,"questionStartingTimeInMillis":1562425937516,"startWindowTimestamp":1562425937351,"answerTimestamp":1562425938351,"endingWindowTimestamp":1562425940351},{"isYes":false,"isTarget":false,"questionStartingTimeInMillis":1562425940353,"startWindowTimestamp":1562425940173,"answerTimestamp":1562425941173,"endingWindowTimestamp":1562425943173},{"isYes":false,"isTarget":false,"questionStartingTimeInMillis":1562425943174,"startWindowTimestamp":1562425943039,"answerTimestamp":1562425944039,"endingWindowTimestamp":1562425946039},{"isYes":false,"isTarget":false,"questionStartingTimeInMillis":1562425946041,"startWindowTimestamp":1562425945785,"answerTimestamp":1562425946785,"endingWindowTimestamp":1562425948785},{"isYes":false,"isTarget":false,"questionStartingTimeInMillis":1562425948787,"startWindowTimestamp":1562425948566,"answerTimestamp":1562425949566,"endingWindowTimestamp":1562425951566},{"isYes":false,"isTarget":false,"questionStartingTimeInMillis":1562425951568,"startWindowTimestamp":1562425951378,"answerTimestamp":1562425952378,"endingWindowTimestamp":1562425954378},{"isYes":false,"isTarget":false,"questionStartingTimeInMillis":1562425954379,"startWindowTimestamp":1562425954089,"answerTimestamp":1562425955089,"endingWindowTimestamp":1562425957089},{"isYes":false,"isTarget":false,"questionStartingTimeInMillis":1562425957091,"startWindowTimestamp":1562425956990,"answerTimestamp":1562425957990,"endingWindowTimestamp":1562425959990},{"isYes":false,"isTarget":true,"questionStartingTimeInMillis":1562425959994,"startWindowTimestamp":1562425959965,"answerTimestamp":1562425960965,"endingWindowTimestamp":1562425962965},{"isYes":false,"isTarget":false,"questionStartingTimeInMillis":1562425962968,"startWindowTimestamp":1562425962659,"answerTimestamp":1562425963659,"endingWindowTimestamp":1562425965659},{"isYes":false,"isTarget":false,"questionStartingTimeInMillis":1562425965661,"startWindowTimestamp":1562425965438,"answerTimestamp":1562425966438,"endingWindowTimestamp":1562425968438},{"isYes":false,"isTarget":false,"questionStartingTimeInMillis":1562425968440,"startWindowTimestamp":1562425968115,"answerTimestamp":1562425969115,"endingWindowTimestamp":1562425971115}]}]}